pdf417as_str/__init__.py
pdf417as_str/convert.py
pdf417as_str/main.py
pdf417as_str-1.1.0.dist-info/LICENSE
pdf417as_str-1.1.0.dist-info/METADATA
pdf417as_str-1.1.0.dist-info/WHEEL
pdf417as_str-1.1.0.dist-info/top_level.txt
pdf417as_str-1.1.0.dist-info/RECORD
