Metadata-Version: 2.1
Name: pdf417as-str
Version: 1.1.0
Summary: Create pdf417 barcode by special font without using images
Home-page: https://github.com/ikvk/pdf417as_str
Author: Vladimir Kaukin
Author-email: KaukinVK@ya.ru
License: LGPLv3
Keywords: pdf417,font,barcode,generate,noimage,python
License-File: LICENSE
